matmul/modules/mult_top.vhd
------------------------------------------------------------------------------ 

-- Title      :  Matrix multiplication

------------------------------------------------------------------------------ 

-- Author     :  Melissa Aguiar

-- Company    : CNPEM LNLS-DIG 

-- Platform   : FPGA-generic 

------------------------------------------------------------------------------- 

-- Description:  Designing a matrix multiplication

------------------------------------------------------------------------------- 

-- Copyright (c) 2012 CNPEM 

-- Licensed under GNU Lesser General Public License (LGPL) v3.0 

------------------------------------------------------------------------------- 

-- Revisions  : 

-- Date        Version  Author                Description 

-- 2021-18-06  1.2      

------------------------------------------------------------------------------

library ieee;
use ieee.std_logic_1164.ALL;
use ieee.numeric_std.all;
use work.array_pkg.all;

entity mult_top is
    port (
        clk_i   : in std_logic;
        rst_i   : in std_logic;
        v_i     : in std_logic; -- sinal de dado valido na entrada
        wr_i    : in std_logic; -- enable pra escrever na memoria
        a_i     : in array_t;   -- entrada a[k] e seu indice
        d_i     : in array_t;   -- termo a entrar na memoria provisoria e seu indice (depois usar a memoria padronizada do hdlmaker)
        c_o     : out integer;  -- resultado do produto interno
        v_o     : out std_logic -- sinal de dado valido na entrada
        );
end mult_top;

architecture behave of mult_top is
    signal result_s : integer := 0;
    signal a_s      : array_t;
    constant M      : integer := 3; -- tamanho exato do vetor a (ate onde k varia)
    signal cnt      : integer := 0;
    
    -- memoria provisoria
    type mem_type is array(0 to M-1) of integer; -- especifica o numero de elementos e o tipo de cada elemento
    signal mem : mem_type := (3, 2, 1); -- criando e inicializando uma memoria para testes
    
begin
    matmul_process : process (clk_i) is
    begin
    
    if rising_edge(clk_i) then
        if(wr_i = '1') then
           mem(d_i(1)) <= d_i(0);
        end if;
        
        if rst_i='0' then
            cnt <= 0;
            result_s <= 0;
            c_o <= 0;
        else
        
            if v_i='1' then
                result_s <= result_s + a_s(0)*mem(a_i(1)); 
                cnt <= cnt + 1; -- contador para saber quando o produto interno foi finalizado
                v_o <= '0';
            end if;
    
            if cnt=M then
                c_o <= result_s;
                cnt <= 0;
                result_s <= 0;
                v_o <= '1'; -- validando a saida de dados
            end if;
        end if;
    end if;
end process;
    a_s <= a_i;
end behave;

matmul/testbench/mult_tb.vhd
library ieee;
use ieee.std_logic_1164.ALL;
use ieee.numeric_std.all;
use work.array_pkg.all;

--library ieee_proposed;

entity mult_tb is
end mult_tb;

architecture behave of mult_tb is

    constant clk_period : time := 10 ns;

    signal clk_s    : std_logic := '0';
    signal rst_s    : std_logic := '0';
    signal wr_s     : std_logic := '0';
    signal v_i_s    : std_logic := '0';
    signal a_s      : array_t; -- vetor contendo o valor da entrada a[k] e seu indice k
    signal d_i_s    : array_t := (0, 0);
    signal c_s      : integer;
    signal v_o_s    : std_logic := '0';

begin

  mult_TOP_INST : mult_top
    port map (
            clk_i   => clk_s,
            rst_i   => rst_s,
            wr_i    => wr_s,
            v_i     => v_i_s,
            a_i     => a_s,
            d_i     => d_i_s,
            c_o     => c_s,
            v_o     => v_o_s
        );

  clk_process : process is 
  begin
    wait for clk_period/2;
        clk_s <= not clk_s;
  end process clk_process;

  process
  begin

    rst_s <= '1';
    
    v_i_s <= '1';
    
    a_s <= (1, 2); -- simulando o vetor de entrada e seu respectivo indice k (se nao inicializasse a_s antes do clk dava erro)
    
    wait for clk_period;
    
--    rst_s <= '0';
    
    a_s <= (2, 1);
    
    wait for clk_period;
    
    v_i_s <= '0';
    
    wait for clk_period;
    
    v_i_s <= '1';
    
    a_s <= (3, 0);
    
    wait for clk_period;
    
    --segundo produto interno (resultado deve ser 14 no primeiro e 10 no segundo)
    
    a_s <= (3, 2);
    
    wait for clk_period;
    
    a_s <= (2, 1);
    
    wait for clk_period;
    
    a_s <= (1, 0);
    
    wait for clk_period;
    wait for clk_period;
    
    if c_s = 14 then 
        report "SUCESS";
     
     elsif c_s = 10 then 
        report "SUCESS"; 
        
     else
        report "FAILURE";
    end if;

    end process;

end behave;

matmul/sim/mult_tb.vcd
$date
  Mon Jun 28 16:19:08 2021
$end
$version
  GHDL v0
$end
$timescale
  1 fs
$end
$scope module standard $end
$upscope $end
$scope module std_logic_1164 $end
$upscope $end
$scope module numeric_std $end
$upscope $end
$scope module array_pkg $end
$upscope $end
$scope module mult_tb $end
$var reg 1 ! clk_s $end
$var reg 1 " rst_s $end
$var reg 1 # wr_s $end
$var reg 1 $ v_i_s $end
$comment a_s is not handled $end
$comment d_i_s is not handled $end
$var integer 32 % c_s $end
$var reg 1 & v_o_s $end
$scope module mult_top_inst $end
$var reg 1 ' clk_i $end
$var reg 1 ( rst_i $end
$var reg 1 ) v_i $end
$var reg 1 * wr_i $end
$comment a_i is not handled $end
$comment d_i is not handled $end
$var integer 32 + c_o $end
$var reg 1 , v_o $end
$var integer 32 - result_s $end
$comment a_s is not handled $end
$var integer 32 . cnt $end
$comment mem is not handled $end
$upscope $end
$upscope $end
$enddefinitions $end
#0
0!
1"
0#
1$
b10000000000000000000000000000000 %
U&
0'
1(
1)
0*
b10000000000000000000000000000000 +
U,
b0 -
b0 .
#5000000
1!
0&
1'
0,
b1 -
b1 .
#10000000
0!
0'
#15000000
1!
1'
b101 -
b10 .
#20000000
0!
0$
0'
0)
#25000000
1!
1'
#30000000
0!
1$
0'
1)
#35000000
1!
1'
b1110 -
b11 .
#40000000
0!
0'
#45000000
1!
b1110 %
1&
1'
b1110 +
1,
b0 -
b0 .
#50000000
0!
0'
#55000000
1!
0&
1'
0,
b100 -
b1 .
#60000000
0!
0'
#65000000
1!
1'
b111 -
b10 .
#70000000
0!
0'
#75000000
1!
1'
b1010 -
b11 .
#80000000
0!
0'
#85000000
1!
b1010 %
1&
1'
b1010 +
1,
b0 -
b0 .
#90000000
0!
0'
#95000000
1!
0&
1'
0,
b100 -
b1 .
#100000000
0!
0$
0'
0)
#105000000
1!
1'
#110000000
0!
1$
0'
1)
#115000000
1!
1'
b1101 -
b10 .
#120000000
0!
0'
#125000000
1!
1'
b10000 -
b11 .
#130000000
0!
0'
#135000000
1!
b10000 %
1&
1'
b10000 +
1,
b0 -
b0 .
#140000000
0!
0'
#145000000
1!
0&
1'
0,
b11 -
b1 .
#150000000
0!
0'
#155000000
1!
1'
b110 -
b10 .
#160000000
0!
0'
#165000000
1!
1'
b111 -
b11 .
#170000000
0!
0'
#175000000
1!
b111 %
1&
1'
b111 +
1,
b0 -
b0 .
#180000000
0!
0$
0'
0)
#185000000
1!
1'
#190000000
0!
1$
0'
1)
#195000000
1!
0&
1'
0,
b1001 -
b1 .
#200000000
0!
0'
#205000000
1!
1'
b1100 -
b10 .
#210000000
0!
0'
#215000000
1!
1'
b10000 -
b11 .
#220000000
0!
0'
#225000000
1!
b10000 %
1&
1'
b10000 +
1,
b0 -
b0 .
#230000000
0!
0'
#235000000
1!
0&
1'
0,
b11 -
b1 .
#240000000
0!
0'
#245000000
1!
1'
b100 -
b10 .
#250000000
0!
0'
#255000000
1!
1'
b1000 -
b11 .
#260000000
0!
0$
0'
0)
#265000000
1!
b1000 %
1&
1'
b1000 +
1,
b0 -
b0 .
#270000000
0!
1$
0'
1)
#275000000
1!
0&
1'
0,
b1001 -
b1 .
#280000000
0!
0'
#285000000
1!
1'
b1100 -
b10 .
#290000000
0!
0'
#295000000
1!
1'
b10000 -
b11 .
#300000000
0!
0'
#305000000
1!
b10000 %
1&
1'
b10000 +
1,
b0 -
b0 .
#310000000
0!
0'
#315000000
1!
0&
1'
0,
b11 -
b1 .
#320000000
0!
0'
#325000000
1!
1'
b100 -
b10 .
#330000000
0!
0'
#335000000
1!
1'
b1000 -
b11 .
#340000000
0!
0$
0'
0)
#345000000
1!
b1000 %
1&
1'
b1000 +
1,
b0 -
b0 .
#350000000
0!
1$
0'
1)
#355000000
1!
0&
1'
0,
b1001 -
b1 .
#360000000
0!
0'
#365000000
1!
1'
b1100 -
b10 .
#370000000
0!
0'
#375000000
1!
1'
b10000 -
b11 .
#380000000
0!
0'
#385000000
1!
b10000 %
1&
1'
b10000 +
1,
b0 -
b0 .
#390000000
0!
0'
#395000000
1!
0&
1'
0,
b11 -
b1 .
#400000000
0!
0'
#405000000
1!
1'
b100 -
b10 .
#410000000
0!
0'
#415000000
1!
1'
b1000 -
b11 .
#420000000
0!
0$
0'
0)
#425000000
1!
b1000 %
1&
1'
b1000 +
1,
b0 -
b0 .
#430000000
0!
1$
0'
1)
#435000000
1!
0&
1'
0,
b1001 -
b1 .
#440000000
0!
0'
#445000000
1!
1'
b1100 -
b10 .
#450000000
0!
0'
#455000000
1!
1'
b10000 -
b11 .
#460000000
0!
0'
#465000000
1!
b10000 %
1&
1'
b10000 +
1,
b0 -
b0 .
#470000000
0!
0'
#475000000
1!
0&
1'
0,
b11 -
b1 .
#480000000
0!
0'
#485000000
1!
1'
b100 -
b10 .
#490000000
0!
0'
#495000000
1!
1'
b1000 -
b11 .
#500000000
0!
0$
0'
0)
#505000000
1!
b1000 %
1&
1'
b1000 +
1,
b0 -
b0 .
#510000000
0!
1$
0'
1)
#515000000
1!
0&
1'
0,
b1001 -
b1 .
#520000000
0!
0'
#525000000
1!
1'
b1100 -
b10 .
#530000000
0!
0'
#535000000
1!
1'
b10000 -
b11 .
#540000000
0!
0'
#545000000
1!
b10000 %
1&
1'
b10000 +
1,
b0 -
b0 .
#550000000
0!
0'
#555000000
1!
0&
1'
0,
b11 -
b1 .
#560000000
0!
0'
#565000000
1!
1'
b100 -
b10 .
#570000000
0!
0'
#575000000
1!
1'
b1000 -
b11 .
#580000000
0!
0$
0'
0)
#585000000
1!
b1000 %
1&
1'
b1000 +
1,
b0 -
b0 .
#590000000
0!
1$
0'
1)
#595000000
1!
0&
1'
0,
b1001 -
b1 .
#600000000
0!
0'
#605000000
1!
1'
b1100 -
b10 .
#610000000
0!
0'
#615000000
1!
1'
b10000 -
b11 .
#620000000
0!
0'
#625000000
1!
b10000 %
1&
1'
b10000 +
1,
b0 -
b0 .
#630000000
0!
0'
#635000000
1!
0&
1'
0,
b11 -
b1 .
#640000000
0!
0'
#645000000
1!
1'
b100 -
b10 .
#650000000
0!
0'
#655000000
1!
1'
b1000 -
b11 .
#660000000
0!
0$
0'
0)
#665000000
1!
b1000 %
1&
1'
b1000 +
1,
b0 -
b0 .
#670000000
0!
1$
0'
1)
#675000000
1!
0&
1'
0,
b1001 -
b1 .
#680000000
0!
0'
#685000000
1!
1'
b1100 -
b10 .
#690000000
0!
0'
#695000000
1!
1'
b10000 -
b11 .
#700000000
0!
0'
#705000000
1!
b10000 %
1&
1'
b10000 +
1,
b0 -
b0 .
#710000000
0!
0'
#715000000
1!
0&
1'
0,
b11 -
b1 .
#720000000
0!
0'
#725000000
1!
1'
b100 -
b10 .
#730000000
0!
0'
#735000000
1!
1'
b1000 -
b11 .
#740000000
0!
0$
0'
0)
#745000000
1!
b1000 %
1&
1'
b1000 +
1,
b0 -
b0 .
#750000000
0!
1$
0'
1)
#755000000
1!
0&
1'
0,
b1001 -
b1 .
#760000000
0!
0'
#765000000
1!
1'
b1100 -
b10 .
#770000000
0!
0'
#775000000
1!
1'
b10000 -
b11 .
#780000000
0!
0'
#785000000
1!
b10000 %
1&
1'
b10000 +
1,
b0 -
b0 .
#790000000
0!
0'
#795000000
1!
0&
1'
0,
b11 -
b1 .
#800000000
0!
0'
#805000000
1!
1'
b100 -
b10 .
#810000000
0!
0'
#815000000
1!
1'
b1000 -
b11 .
#820000000
0!
0$
0'
0)
#825000000
1!
b1000 %
1&
1'
b1000 +
1,
b0 -
b0 .
#830000000
0!
1$
0'
1)
#835000000
1!
0&
1'
0,
b1001 -
b1 .
#840000000
0!
0'
#845000000
1!
1'
b1100 -
b10 .
#850000000
0!
0'
#855000000
1!
1'
b10000 -
b11 .
#860000000
0!
0'
#865000000
1!
b10000 %
1&
1'
b10000 +
1,
b0 -
b0 .
#870000000
0!
0'
#875000000
1!
0&
1'
0,
b11 -
b1 .
#880000000
0!
0'
#885000000
1!
1'
b100 -
b10 .
#890000000
0!
0'
#895000000
1!
1'
b1000 -
b11 .
#900000000
0!
0$
0'
0)
#905000000
1!
b1000 %
1&
1'
b1000 +
1,
b0 -
b0 .
#910000000
0!
1$
0'
1)
#915000000
1!
0&
1'
0,
b1001 -
b1 .
#920000000
0!
0'
#925000000
1!
1'
b1100 -
b10 .
#930000000
0!
0'
#935000000
1!
1'
b10000 -
b11 .
#940000000
0!
0'
#945000000
1!
b10000 %
1&
1'
b10000 +
1,
b0 -
b0 .
#950000000
0!
0'
#955000000
1!
0&
1'
0,
b11 -
b1 .
#960000000
0!
0'
#965000000
1!
1'
b100 -
b10 .
#970000000
0!
0'
#975000000
1!
1'
b1000 -
b11 .
#980000000
0!
0$
0'
0)
#985000000
1!
b1000 %
1&
1'
b1000 +
1,
b0 -
b0 .
#990000000
0!
1$
0'
1)
#995000000
1!
0&
1'
0,
b1001 -
b1 .
