matmul/modules/matmul.vhd
------------------------------------------------------------------------------

-- Title      :  Matrix multiplication

------------------------------------------------------------------------------

-- Author     :  Melissa Aguiar

-- Company    : CNPEM LNLS-DIG

-- Platform   : FPGA-generic

-------------------------------------------------------------------------------

-- Description:  Matrix multiplication module for the Fast Orbit Feedback

-------------------------------------------------------------------------------

-- Copyright (c) 2020 CNPEM

-- Licensed under GNU Lesser General Public License (LGPL) v3.0

-------------------------------------------------------------------------------

-- Revisions  :

-- Date        Version  Author                Description

-- 2021-29-06  1.0      melissa.aguiar        Created

------------------------------------------------------------------------------

library ieee;
use ieee.std_logic_1164.ALL;
use ieee.numeric_std.all;

library work;
use work.mult_pkg.all;

entity matmul is
  generic(
  g_BITS : natural := 32
  );
  port (
    -- Core clock
    clk_i                           : in std_logic;
    -- Reset
    rst_n_i                         : in std_logic;
    -- Data valid input
    v_i                             : in std_logic;
    -- Input a[k] and index k
    a_i                             : in t_record;
    -- Input b[k]
    b_i                             : in signed(g_BITS-1 downto 0);
    -- Result output
    c_o                             : out signed(g_BITS-1 downto 0);
    -- Data valid output
    v_o                             : out std_logic
    );
end matmul;

architecture behave of matmul is
  signal result_s        : signed(2*g_BITS-1 downto 0) := (others =>'0');
  signal a_s             : t_record;
  constant cnt_max       : integer := 3;
  signal cnt             : integer range 0 to cnt_max+1 := 0;

begin
  matmul_process : process (clk_i) is
  begin

  if rising_edge(clk_i) then
    if rst_n_i='0' then
      cnt <= 0;
      result_s <= (others =>'0');
      c_o <= (others =>'0');
    else

      if v_i='1' then
        result_s <= result_s + a_s.r_a*b_i; -- Add pipeline stages here
        cnt <= cnt + 1;
        v_o <= '0';
      end if;

      if cnt=cnt_max then
      c_o <= resize(result_s, c_o'length); -- Studies to round the output
        cnt <= 0;
        result_s <= (others =>'0');
        v_o <= '1';
      end if;
    end if;
  end if;
end process;
    a_s <= a_i;
end behave;

matmul/testbench/mult_tb.vhd
------------------------------------------------------------------------------

-- Title      :  Matrix multiplication testbench

------------------------------------------------------------------------------

-- Author     :  Melissa Aguiar

-- Company    : CNPEM LNLS-DIG

-- Platform   : FPGA-generic

-------------------------------------------------------------------------------

-- Description:  Testbench for the matrix multiplication core

-------------------------------------------------------------------------------

-- Copyright (c) 2020 CNPEM

-- Licensed under GNU Lesser General Public License (LGPL) v3.0

-------------------------------------------------------------------------------

-- Revisions  :

-- Date        Version  Author                Description

-- 2021-29-06  1.0      melissa.aguiar        Created

------------------------------------------------------------------------------

library ieee;
use ieee.std_logic_1164.ALL;
use ieee.numeric_std.all;

library work;
use work.mult_pkg.all;

entity mult_tb is
end mult_tb;

architecture behave of mult_tb is

  constant clk_period : time := 10 ns;

  signal clk_s    : std_logic := '0';
  signal rst_s    : std_logic := '0';
  signal v_i_s    : std_logic := '0';
  signal a_s      : t_record;
  signal b_s      : signed(32-1 downto 0) := (others => '0');
  signal c_s      : signed(32-1 downto 0);
  signal v_o_s    : std_logic := '0';

begin

  matmul_INST : matmul
  port map (
    clk_i   => clk_s,
    rst_n_i => rst_s,
    v_i     => v_i_s,
    a_i     => a_s,
    b_i     => b_s,
    c_o     => c_s,
    v_o     => v_o_s
    );

  clk_process : process is
  begin
    wait for clk_period/2;
    clk_s <= not clk_s;
  end process clk_process;

  process
  begin

  rst_s <= '1';

  v_i_s <= '1';

  a_s.r_a <= to_signed(1, a_s.r_a'length);
  a_s.r_k <= to_unsigned(2, a_s.r_k'length);
  b_s <= to_signed(1, b_s'length);

  wait for clk_period;

  a_s.r_a <= to_signed(2, a_s.r_a'length);
  a_s.r_k <= to_unsigned(1, a_s.r_k'length);

  wait for clk_period;

  v_i_s <= '0';

  wait for clk_period;

  v_i_s <= '1';

  a_s.r_a <= to_signed(3, a_s.r_a'length);
  a_s.r_k <= to_unsigned(0, a_s.r_k'length);

  wait for clk_period;

  a_s.r_a <= to_signed(3, a_s.r_a'length);
  a_s.r_k <= to_unsigned(2, a_s.r_k'length);
  b_s <= to_signed(2, b_s'length);

  wait for clk_period;

  a_s.r_a <= to_signed(2, a_s.r_a'length);
  a_s.r_k <= to_unsigned(1, a_s.r_k'length);

  wait for clk_period;

  a_s.r_a <= to_signed(1, a_s.r_a'length);
  a_s.r_k <= to_unsigned(0, a_s.r_k'length);

  wait for clk_period;
  wait for clk_period;

  if c_s = to_signed(6, c_s'length) then
      report "SUCESS";

    else
      report "FAILURE";
  end if;

  end process;

end behave;

matmul/sim/mult_tb.vcd
$date
  Tue Jun 29 14:55:27 2021
$end
$version
  GHDL v0
$end
$timescale
  1 fs
$end
$scope module standard $end
$upscope $end
$scope module std_logic_1164 $end
$upscope $end
$scope module numeric_std $end
$upscope $end
$scope module mult_pkg $end
$upscope $end
$scope module mult_tb $end
$var reg 1 ! clk_s $end
$var reg 1 " rst_s $end
$var reg 1 # v_i_s $end
$comment a_s is not handled $end
$var reg 32 $ b_s[31:0] $end
$var reg 32 % c_s[31:0] $end
$var reg 1 & v_o_s $end
$scope module matmul_inst $end
$var reg 1 ' clk_i $end
$var reg 1 ( rst_n_i $end
$var reg 1 ) v_i $end
$comment a_i is not handled $end
$var reg 32 * b_i[31:0] $end
$var reg 32 + c_o[31:0] $end
$var reg 1 , v_o $end
$var reg 64 - result_s[63:0] $end
$comment a_s is not handled $end
$var integer 32 . cnt $end
$upscope $end
$upscope $end
$enddefinitions $end
#0
0!
1"
1#
b00000000000000000000000000000001 $
bUUUUUUUUUUUUUUUUUUUUUUUUUUUUUUUU %
U&
0'
1(
1)
b00000000000000000000000000000001 *
bUUUUUUUUUUUUUUUUUUUUUUUUUUUUUUUU +
U,
b0000000000000000000000000000000000000000000000000000000000000000 -
b0 .
#5000000
1!
0&
1'
0,
b0000000000000000000000000000000000000000000000000000000000000001 -
b1 .
#10000000
0!
0'
#15000000
1!
1'
b0000000000000000000000000000000000000000000000000000000000000011 -
b10 .
#20000000
0!
0#
0'
0)
#25000000
1!
1'
#30000000
0!
1#
0'
1)
#35000000
1!
1'
b0000000000000000000000000000000000000000000000000000000000000110 -
b11 .
#40000000
0!
b00000000000000000000000000000010 $
0'
b00000000000000000000000000000010 *
#45000000
1!
b00000000000000000000000000000110 %
1&
1'
b00000000000000000000000000000110 +
1,
b0000000000000000000000000000000000000000000000000000000000000000 -
b0 .
#50000000
0!
0'
#55000000
1!
0&
1'
0,
b0000000000000000000000000000000000000000000000000000000000000100 -
b1 .
#60000000
0!
0'
#65000000
1!
1'
b0000000000000000000000000000000000000000000000000000000000000110 -
b10 .
#70000000
0!
0'
#75000000
1!
1'
b0000000000000000000000000000000000000000000000000000000000001000 -
b11 .
#80000000
0!
b00000000000000000000000000000001 $
0'
b00000000000000000000000000000001 *
#85000000
1!
b00000000000000000000000000001000 %
1&
1'
b00000000000000000000000000001000 +
1,
b0000000000000000000000000000000000000000000000000000000000000000 -
b0 .
#90000000
0!
0'
#95000000
1!
0&
1'
0,
b0000000000000000000000000000000000000000000000000000000000000010 -
b1 .
#100000000
0!
0#
0'
0)
#105000000
1!
1'
#110000000
0!
1#
0'
1)
#115000000
1!
1'
b0000000000000000000000000000000000000000000000000000000000000101 -
b10 .
#120000000
0!
b00000000000000000000000000000010 $
0'
b00000000000000000000000000000010 *
#125000000
1!
1'
b0000000000000000000000000000000000000000000000000000000000001011 -
b11 .
#130000000
0!
0'
#135000000
1!
b00000000000000000000000000001011 %
1&
1'
b00000000000000000000000000001011 +
1,
b0000000000000000000000000000000000000000000000000000000000000000 -
b0 .
#140000000
0!
0'
#145000000
1!
0&
1'
0,
b0000000000000000000000000000000000000000000000000000000000000010 -
b1 .
#150000000
0!
0'
#155000000
1!
1'
b0000000000000000000000000000000000000000000000000000000000000100 -
b10 .
#160000000
0!
b00000000000000000000000000000001 $
0'
b00000000000000000000000000000001 *
#165000000
1!
1'
b0000000000000000000000000000000000000000000000000000000000000101 -
b11 .
#170000000
0!
0'
#175000000
1!
b00000000000000000000000000000101 %
1&
1'
b00000000000000000000000000000101 +
1,
b0000000000000000000000000000000000000000000000000000000000000000 -
b0 .
#180000000
0!
0#
0'
0)
#185000000
1!
1'
#190000000
0!
1#
0'
1)
#195000000
1!
0&
1'
0,
b0000000000000000000000000000000000000000000000000000000000000011 -
b1 .
#200000000
0!
b00000000000000000000000000000010 $
0'
b00000000000000000000000000000010 *
#205000000
1!
1'
b0000000000000000000000000000000000000000000000000000000000001001 -
b10 .
#210000000
0!
0'
#215000000
1!
1'
b0000000000000000000000000000000000000000000000000000000000001101 -
b11 .
#220000000
0!
0'
#225000000
1!
b00000000000000000000000000001101 %
1&
1'
b00000000000000000000000000001101 +
1,
b0000000000000000000000000000000000000000000000000000000000000000 -
b0 .
#230000000
0!
0'
#235000000
1!
0&
1'
0,
b0000000000000000000000000000000000000000000000000000000000000010 -
b1 .
#240000000
0!
b00000000000000000000000000000001 $
0'
b00000000000000000000000000000001 *
#245000000
1!
1'
b0000000000000000000000000000000000000000000000000000000000000011 -
b10 .
#250000000
0!
0'
#255000000
1!
1'
b0000000000000000000000000000000000000000000000000000000000000101 -
b11 .
#260000000
0!
0#
0'
0)
#265000000
1!
b00000000000000000000000000000101 %
1&
1'
b00000000000000000000000000000101 +
1,
b0000000000000000000000000000000000000000000000000000000000000000 -
b0 .
#270000000
0!
1#
0'
1)
#275000000
1!
0&
1'
0,
b0000000000000000000000000000000000000000000000000000000000000011 -
b1 .
#280000000
0!
b00000000000000000000000000000010 $
0'
b00000000000000000000000000000010 *
#285000000
1!
1'
b0000000000000000000000000000000000000000000000000000000000001001 -
b10 .
#290000000
0!
0'
#295000000
1!
1'
b0000000000000000000000000000000000000000000000000000000000001101 -
b11 .
#300000000
0!
0'
#305000000
1!
b00000000000000000000000000001101 %
1&
1'
b00000000000000000000000000001101 +
1,
b0000000000000000000000000000000000000000000000000000000000000000 -
b0 .
#310000000
0!
0'
#315000000
1!
0&
1'
0,
b0000000000000000000000000000000000000000000000000000000000000010 -
b1 .
#320000000
0!
b00000000000000000000000000000001 $
0'
b00000000000000000000000000000001 *
#325000000
1!
1'
b0000000000000000000000000000000000000000000000000000000000000011 -
b10 .
#330000000
0!
0'
#335000000
1!
1'
b0000000000000000000000000000000000000000000000000000000000000101 -
b11 .
#340000000
0!
0#
0'
0)
#345000000
1!
b00000000000000000000000000000101 %
1&
1'
b00000000000000000000000000000101 +
1,
b0000000000000000000000000000000000000000000000000000000000000000 -
b0 .
#350000000
0!
1#
0'
1)
#355000000
1!
0&
1'
0,
b0000000000000000000000000000000000000000000000000000000000000011 -
b1 .
#360000000
0!
b00000000000000000000000000000010 $
0'
b00000000000000000000000000000010 *
#365000000
1!
1'
b0000000000000000000000000000000000000000000000000000000000001001 -
b10 .
#370000000
0!
0'
#375000000
1!
1'
b0000000000000000000000000000000000000000000000000000000000001101 -
b11 .
#380000000
0!
0'
#385000000
1!
b00000000000000000000000000001101 %
1&
1'
b00000000000000000000000000001101 +
1,
b0000000000000000000000000000000000000000000000000000000000000000 -
b0 .
#390000000
0!
0'
#395000000
1!
0&
1'
0,
b0000000000000000000000000000000000000000000000000000000000000010 -
b1 .
#400000000
0!
b00000000000000000000000000000001 $
0'
b00000000000000000000000000000001 *
#405000000
1!
1'
b0000000000000000000000000000000000000000000000000000000000000011 -
b10 .
#410000000
0!
0'
#415000000
1!
1'
b0000000000000000000000000000000000000000000000000000000000000101 -
b11 .
#420000000
0!
0#
0'
0)
#425000000
1!
b00000000000000000000000000000101 %
1&
1'
b00000000000000000000000000000101 +
1,
b0000000000000000000000000000000000000000000000000000000000000000 -
b0 .
#430000000
0!
1#
0'
1)
#435000000
1!
0&
1'
0,
b0000000000000000000000000000000000000000000000000000000000000011 -
b1 .
#440000000
0!
b00000000000000000000000000000010 $
0'
b00000000000000000000000000000010 *
#445000000
1!
1'
b0000000000000000000000000000000000000000000000000000000000001001 -
b10 .
#450000000
0!
0'
#455000000
1!
1'
b0000000000000000000000000000000000000000000000000000000000001101 -
b11 .
#460000000
0!
0'
#465000000
1!
b00000000000000000000000000001101 %
1&
1'
b00000000000000000000000000001101 +
1,
b0000000000000000000000000000000000000000000000000000000000000000 -
b0 .
#470000000
0!
0'
#475000000
1!
0&
1'
0,
b0000000000000000000000000000000000000000000000000000000000000010 -
b1 .
#480000000
0!
b00000000000000000000000000000001 $
0'
b00000000000000000000000000000001 *
#485000000
1!
1'
b0000000000000000000000000000000000000000000000000000000000000011 -
b10 .
#490000000
0!
0'
#495000000
1!
1'
b0000000000000000000000000000000000000000000000000000000000000101 -
b11 .
#500000000
0!
0#
0'
0)
#505000000
1!
b00000000000000000000000000000101 %
1&
1'
b00000000000000000000000000000101 +
1,
b0000000000000000000000000000000000000000000000000000000000000000 -
b0 .
#510000000
0!
1#
0'
1)
#515000000
1!
0&
1'
0,
b0000000000000000000000000000000000000000000000000000000000000011 -
b1 .
#520000000
0!
b00000000000000000000000000000010 $
0'
b00000000000000000000000000000010 *
#525000000
1!
1'
b0000000000000000000000000000000000000000000000000000000000001001 -
b10 .
#530000000
0!
0'
#535000000
1!
1'
b0000000000000000000000000000000000000000000000000000000000001101 -
b11 .
#540000000
0!
0'
#545000000
1!
b00000000000000000000000000001101 %
1&
1'
b00000000000000000000000000001101 +
1,
b0000000000000000000000000000000000000000000000000000000000000000 -
b0 .
#550000000
0!
0'
#555000000
1!
0&
1'
0,
b0000000000000000000000000000000000000000000000000000000000000010 -
b1 .
#560000000
0!
b00000000000000000000000000000001 $
0'
b00000000000000000000000000000001 *
#565000000
1!
1'
b0000000000000000000000000000000000000000000000000000000000000011 -
b10 .
#570000000
0!
0'
#575000000
1!
1'
b0000000000000000000000000000000000000000000000000000000000000101 -
b11 .
#580000000
0!
0#
0'
0)
#585000000
1!
b00000000000000000000000000000101 %
1&
1'
b00000000000000000000000000000101 +
1,
b0000000000000000000000000000000000000000000000000000000000000000 -
b0 .
#590000000
0!
1#
0'
1)
#595000000
1!
0&
1'
0,
b0000000000000000000000000000000000000000000000000000000000000011 -
b1 .
#600000000
0!
b00000000000000000000000000000010 $
0'
b00000000000000000000000000000010 *
#605000000
1!
1'
b0000000000000000000000000000000000000000000000000000000000001001 -
b10 .
#610000000
0!
0'
#615000000
1!
1'
b0000000000000000000000000000000000000000000000000000000000001101 -
b11 .
#620000000
0!
0'
#625000000
1!
b00000000000000000000000000001101 %
1&
1'
b00000000000000000000000000001101 +
1,
b0000000000000000000000000000000000000000000000000000000000000000 -
b0 .
#630000000
0!
0'
#635000000
1!
0&
1'
0,
b0000000000000000000000000000000000000000000000000000000000000010 -
b1 .
#640000000
0!
b00000000000000000000000000000001 $
0'
b00000000000000000000000000000001 *
#645000000
1!
1'
b0000000000000000000000000000000000000000000000000000000000000011 -
b10 .
#650000000
0!
0'
#655000000
1!
1'
b0000000000000000000000000000000000000000000000000000000000000101 -
b11 .
#660000000
0!
0#
0'
0)
#665000000
1!
b00000000000000000000000000000101 %
1&
1'
b00000000000000000000000000000101 +
1,
b0000000000000000000000000000000000000000000000000000000000000000 -
b0 .
#670000000
0!
1#
0'
1)
#675000000
1!
0&
1'
0,
b0000000000000000000000000000000000000000000000000000000000000011 -
b1 .
#680000000
0!
b00000000000000000000000000000010 $
0'
b00000000000000000000000000000010 *
#685000000
1!
1'
b0000000000000000000000000000000000000000000000000000000000001001 -
b10 .
#690000000
0!
0'
#695000000
1!
1'
b0000000000000000000000000000000000000000000000000000000000001101 -
b11 .
#700000000
0!
0'
#705000000
1!
b00000000000000000000000000001101 %
1&
1'
b00000000000000000000000000001101 +
1,
b0000000000000000000000000000000000000000000000000000000000000000 -
b0 .
#710000000
0!
0'
#715000000
1!
0&
1'
0,
b0000000000000000000000000000000000000000000000000000000000000010 -
b1 .
#720000000
0!
b00000000000000000000000000000001 $
0'
b00000000000000000000000000000001 *
#725000000
1!
1'
b0000000000000000000000000000000000000000000000000000000000000011 -
b10 .
#730000000
0!
0'
#735000000
1!
1'
b0000000000000000000000000000000000000000000000000000000000000101 -
b11 .
#740000000
0!
0#
0'
0)
#745000000
1!
b00000000000000000000000000000101 %
1&
1'
b00000000000000000000000000000101 +
1,
b0000000000000000000000000000000000000000000000000000000000000000 -
b0 .
#750000000
0!
1#
0'
1)
#755000000
1!
0&
1'
0,
b0000000000000000000000000000000000000000000000000000000000000011 -
b1 .
#760000000
0!
b00000000000000000000000000000010 $
0'
b00000000000000000000000000000010 *
#765000000
1!
1'
b0000000000000000000000000000000000000000000000000000000000001001 -
b10 .
#770000000
0!
0'
#775000000
1!
1'
b0000000000000000000000000000000000000000000000000000000000001101 -
b11 .
#780000000
0!
0'
#785000000
1!
b00000000000000000000000000001101 %
1&
1'
b00000000000000000000000000001101 +
1,
b0000000000000000000000000000000000000000000000000000000000000000 -
b0 .
#790000000
0!
0'
#795000000
1!
0&
1'
0,
b0000000000000000000000000000000000000000000000000000000000000010 -
b1 .
#800000000
0!
b00000000000000000000000000000001 $
0'
b00000000000000000000000000000001 *
#805000000
1!
1'
b0000000000000000000000000000000000000000000000000000000000000011 -
b10 .
#810000000
0!
0'
#815000000
1!
1'
b0000000000000000000000000000000000000000000000000000000000000101 -
b11 .
#820000000
0!
0#
0'
0)
#825000000
1!
b00000000000000000000000000000101 %
1&
1'
b00000000000000000000000000000101 +
1,
b0000000000000000000000000000000000000000000000000000000000000000 -
b0 .
#830000000
0!
1#
0'
1)
#835000000
1!
0&
1'
0,
b0000000000000000000000000000000000000000000000000000000000000011 -
b1 .
#840000000
0!
b00000000000000000000000000000010 $
0'
b00000000000000000000000000000010 *
#845000000
1!
1'
b0000000000000000000000000000000000000000000000000000000000001001 -
b10 .
#850000000
0!
0'
#855000000
1!
1'
b0000000000000000000000000000000000000000000000000000000000001101 -
b11 .
#860000000
0!
0'
#865000000
1!
b00000000000000000000000000001101 %
1&
1'
b00000000000000000000000000001101 +
1,
b0000000000000000000000000000000000000000000000000000000000000000 -
b0 .
#870000000
0!
0'
#875000000
1!
0&
1'
0,
b0000000000000000000000000000000000000000000000000000000000000010 -
b1 .
#880000000
0!
b00000000000000000000000000000001 $
0'
b00000000000000000000000000000001 *
#885000000
1!
1'
b0000000000000000000000000000000000000000000000000000000000000011 -
b10 .
#890000000
0!
0'
#895000000
1!
1'
b0000000000000000000000000000000000000000000000000000000000000101 -
b11 .
#900000000
0!
0#
0'
0)
#905000000
1!
b00000000000000000000000000000101 %
1&
1'
b00000000000000000000000000000101 +
1,
b0000000000000000000000000000000000000000000000000000000000000000 -
b0 .
#910000000
0!
1#
0'
1)
#915000000
1!
0&
1'
0,
b0000000000000000000000000000000000000000000000000000000000000011 -
b1 .
#920000000
0!
b00000000000000000000000000000010 $
0'
b00000000000000000000000000000010 *
#925000000
1!
1'
b0000000000000000000000000000000000000000000000000000000000001001 -
b10 .
#930000000
0!
0'
#935000000
1!
1'
b0000000000000000000000000000000000000000000000000000000000001101 -
b11 .
#940000000
0!
0'
#945000000
1!
b00000000000000000000000000001101 %
1&
1'
b00000000000000000000000000001101 +
1,
b0000000000000000000000000000000000000000000000000000000000000000 -
b0 .
#950000000
0!
0'
#955000000
1!
0&
1'
0,
b0000000000000000000000000000000000000000000000000000000000000010 -
b1 .
#960000000
0!
b00000000000000000000000000000001 $
0'
b00000000000000000000000000000001 *
#965000000
1!
1'
b0000000000000000000000000000000000000000000000000000000000000011 -
b10 .
#970000000
0!
0'
#975000000
1!
1'
b0000000000000000000000000000000000000000000000000000000000000101 -
b11 .
#980000000
0!
0#
0'
0)
#985000000
1!
b00000000000000000000000000000101 %
1&
1'
b00000000000000000000000000000101 +
1,
b0000000000000000000000000000000000000000000000000000000000000000 -
b0 .
#990000000
0!
1#
0'
1)
#995000000
1!
0&
1'
0,
b0000000000000000000000000000000000000000000000000000000000000011 -
b1 .
#1000000000
0!
b00000000000000000000000000000010 $
0'
b00000000000000000000000000000010 *
